Workbook

Sheet Contexte
B2: PRICING ET ANALYSE DE RISQUE OBLIGATAIRE
B4: Calcul du taux actuariel · Duration de Macaulay · Sensibilité | 3 structures obligataires comparées
B6: 1. CONTEXTE DU PROJET
B7: Ce projet s'inscrit dans le cadre d'un cours de Finance de Marché . L'objectif est de maîtriser le pricing d'obligations et l'analyse de leur risque de taux, en modélisant trois structures obligataires distinctes et en calculant pour chacune le taux actuariel, la duration de Macaulay et la sensibilité.
B9: 2. LES TROIS OBLIGATIONS ANALYSÉES
B10: Obligation 1 — Amortissement constant | C10: Taux facial : 7 % | Prix d'achat : 0,97 | Maturité : 5 ans Remboursement par séries égales (20 % du capital par an) Taux actuariel : 8,19 % | Duration : 2,73 | Sensibilité : 2,52
B11: Obligation 2 — In fine au pair | C11: Taux facial : 13 % | Prix d'achat : 1,20 | Maturité : 5 ans Remboursement du capital en totalité à l'échéance Taux actuariel : 7,99 % | Duration : 4,07 | Sensibilité : 3,77
B12: Obligation 3 — Zéro-coupon | C12: Taux facial : 0 % | Prix d'achat : 0,67 | Maturité : 5 ans Aucun coupon versé , remboursement unique à l'échéance Taux actuariel : 8,34 % | Duration : 5 (= maturité) | Sensibilité : 4,62
B14: 3. CONCEPTS CLÉS MOBILISÉS
B15: Taux actuariel | C15: Taux d'actualisation qui égalise la valeur actuelle des flux futurs (coupons + remboursement) au prix d'achat de l'obligation. Il représente le rendement réel de l'investisseur.
B16: Duration de Macaulay | C16: Durée de vie moyenne pondérée des flux, exprimée en années. Plus la duration est élevée, plus l'obligation est sensible aux variations de taux. Propriété clé : la duration d'un zéro-coupon est toujours égale à sa maturité.
B17: Sensibilité | C17: Mesure la variation en % du prix de l'obligation pour une hausse de taux de 1 %. Sensibilité = − Duration / (1 + taux actuariel). Une sensibilité élevée indique un risque de taux plus important.
B19: 4. ENSEIGNEMENTS COMPARATIFS
B20: • L'obligation à amortissement constant (Oblig. 1) présente la duration la plus faible (2,73) car les flux sont répartis régulièrement dans le temps → risque de taux limité. • L'obligation in fine (Oblig. 2) concentre le remboursement à l'échéance → duration plus élevée (4,07). • Le zéro-coupon (Oblig. 3) affiche la sensibilité maximale (4,62) : sans coupon, l'investisseur attend 5 ans pour récupérer son capital → exposition maximale au risque de taux.
B22: 5. STRUCTURE DU FICHIER
B23: Onglet Récapitulatif | C23: Synthèse des 3 obligations : hypothèses, taux actuariel, duration et sensibilité côte à côte
B24: Onglet Obligation 1 | C24: Tableau d'amortissement complet, actualisation des flux, calcul de la duration et sensibilité
B25: Onglet Obligation 2 | C25: Tableau des flux in fine, actualisation, duration et sensibilité
B26: Onglet Obligation 3 | C26: Zéro-coupon : flux unique en année 5, duration = maturité, sensibilité maximale

Sheet Obligation 1 Amort. Constant
A2: OBLIGATION 1: AMORTISSEMENT CONSTANT
A4: HYPOTHESES
A5: Prix d'achat | B5: 0.97
A6: Maturité | B6: 5 ans
A7: Taux facial | B7: 0.07
A8: Type de remboursement | B8: Séries égales
A9: Taux actuariel | B9: 0.0819
A13: TABLEAU DES FLUX ET ACTUALISATION
A14: Année | B14: Restant dû | C14: Amortissement | D14: Intérêts | E14: Annuité | F14: Flux actualisé | G14: Durée pondérée par flux actu
A15: 1 | B15: 100 | C15: =$B$15/5 -> 20 | D15: =$B$7*B15 -> 7 | E15: =C15+D15 -> 27 | F15: =E15/(1+$B$9)^A15 -> 24.956096 | G15: =F15*A15 -> 24.956096
A16: 2 | B16: 80 | C16: =$B$15/5 -> 20 | D16: =$B$7*B16 -> 5.6 | E16: =C16+D16 -> 25.6 | F16: =E16/(1+$B$9)^A16 -> 21.870853 | G16: =F16*A16 -> 43.741706
A17: 3 | B17: 60 | C17: =$B$15/5 -> 20 | D17: =$B$7*B17 -> 4.2 | E17: =C17+D17 -> 24.2 | F17: =E17/(1+$B$9)^A17 -> 19.109706 | G17: =F17*A17 -> 57.329118
A18: 4 | B18: 40 | C18: =$B$15/5 -> 20 | D18: =$B$7*B18 -> 2.8 | E18: =C18+D18 -> 22.8 | F18: =E18/(1+$B$9)^A18 -> 16.641266 | G18: =F18*A18 -> 66.565064
A19: 5 | B19: 20 | C19: =$B$15/5 -> 20 | D19: =$B$7*B19 -> 1.4 | E19: =C19+D19 -> 21.4 | F19: =E19/(1+$B$9)^A19 -> 14.43704 | G19: =F19*A19 -> 72.185202
A20: TOTAL | F20: =SUM(F15:F19) -> 97.014961 | G20: =SUM(G15:G19) -> 264.77719
F23: Duration | G23: =G20/F20 -> 2.7292408
F24: Sensibilité | G24: =G23/(1+B9) -> 2.5226368

Sheet Obligation 2 Amort. In fine
A1: OBLIGATION 2 : AMORTISSEMENT IN FINE
A3: HYPOTHESES
A4: Prix d'achat | B4: 1.2
A5: Maturité | B5: 5 ans
A6: Taux facial | B6: 0.13
A7: Type de remboursement | B7: In Fine au pair
A8: Taux actuariel | B8: 0.0799
A12: TABLEAU DES FLUX ET ACTUALISATION
A13: Année | B13: Restant dû | C13: Amortissement | D13: Intérêts | E13: Annuité | F13: Flux actualisé | G13: Durée pondérée par flux actu
A14: 1 | B14: 100 | C14: 0 | D14: =$B$6*B14 -> 13 | E14: =C14+D14 -> 13 | F14: =E14/(1+$B$8)^A14 -> 12.038152 | G14: =F14*A14 -> 12.038152
A15: 2 | B15: 100 | C15: 0 | D15: =$B$6*B15 -> 13 | E15: =C15+D15 -> 13 | F15: =E15/(1+$B$8)^A15 -> 11.147469 | G15: =F15*A15 -> 22.294938
A16: 3 | B16: 100 | C16: 0 | D16: =$B$6*B16 -> 13 | E16: =C16+D16 -> 13 | F16: =E16/(1+$B$8)^A16 -> 10.322686 | G16: =F16*A16 -> 30.968059
A17: 4 | B17: 100 | C17: 0 | D17: =$B$6*B17 -> 13 | E17: =C17+D17 -> 13 | F17: =E17/(1+$B$8)^A17 -> 9.5589279 | G17: =F17*A17 -> 38.235712
A18: 5 | B18: 100 | C18: 100 | D18: =$B$6*B18 -> 13 | E18: =C18+D18 -> 113 | F18: =E18/(1+$B$8)^A18 -> 76.941516 | G18: =F18*A18 -> 384.70758
A19: TOTAL | F19: =SUM(F14:F18) -> 120.00875 | G19: =SUM(G14:G18) -> 488.24444
F22: Duration | G22: =G19/F19 -> 4.068407
F23: Sensibilité | G23: =G22/(1+B8) -> 3.7673923

Sheet Obligation 3 Amort. Zero coupon
A1: OBLIGATION 3 : AMORTISSEMENT ZERO COUPON
A3: HYPOTHESES
A4: Prix d'achat | B4: 0.67
A5: Maturité | B5: 5 ans
A6: Taux facial | B6: 0
A7: Type de remboursement | B7: In Fine au pair
A8: Taux actuariel | B8: 0.0834
A12: TABLEAU DES FLUX ET ACTUALISATION
A13: Année | B13: Restant dû | C13: Amortissement | D13: Intérêts | E13: Annuité | F13: Flux actualisé | G13: Durée pondérée par flux actu
A14: 1 | B14: 100 | C14: 0 | D14: =$B$6*B14 -> 0 | E14: =C14+D14 -> 0 | F14: =E14/(1+$B$8)^A14 -> 0 | G14: =F14*A14 -> 0
A15: 2 | B15: 100 | C15: 0 | D15: =$B$6*B15 -> 0 | E15: =C15+D15 -> 0 | F15: =E15/(1+$B$8)^A15 -> 0 | G15: =F15*A15 -> 0
A16: 3 | B16: 100 | C16: 0 | D16: =$B$6*B16 -> 0 | E16: =C16+D16 -> 0 | F16: =E16/(1+$B$8)^A16 -> 0 | G16: =F16*A16 -> 0
A17: 4 | B17: 100 | C17: 0 | D17: =$B$6*B17 -> 0 | E17: =C17+D17 -> 0 | F17: =E17/(1+$B$8)^A17 -> 0 | G17: =F17*A17 -> 0
A18: 5 | B18: 100 | C18: 100 | D18: =$B$6*B18 -> 0 | E18: =C18+D18 -> 100 | F18: =E18/(1+$B$8)^A18 -> 66.997075 | G18: =F18*A18 -> 334.98538
A19: TOTAL | F19: =SUM(F14:F18) -> 66.997075 | G19: =SUM(G14:G18) -> 334.98538
F22: Duration | G22: =G19/F19 -> 5
F23: Sensibilité | G23: =G22/(1+B8) -> 4.6151006

Sheet Récapitulatif.
A1: RÉCAPITULATIF :COMPARAISON DES 3 OBLIGATIONS
B4: Obligation 1 Amortissement constant | C4: Obligation 2 In fine | D4: Obligation 3 Zéro-coupon
A5: Prix d'achat | B5: 0.97 | C5: 1.2 | D5: 0.67
A6: Maturité | B6: 5 ans | C6: 5 ans | D6: 5 ans
A7: Taux facial | B7: 0.07 | C7: 0.13 | D7: 0
A8: Type de remboursement | B8: Séries égales | C8: In fine au pair | D8: In fine au pair
A9: Taux actuariel | B9: 0.0819 | C9: 0.0799 | D9: 0.0834
A10: Duration (années) | B10: ='Obligation 1 Amort. Constant'!G23 -> 2.7292408 | C10: ='Obligation 3 Amort. Zero coupon'!G22 -> 5 | D10: ='Obligation 3 Amort. Zero coupon'!G22 -> 5
A11: Sensibilité | B11: ='Obligation 1 Amort. Constant'!G24 -> 2.5226368 | C11: ='Obligation 2 Amort. In fine'!G23 -> 3.7673923 | D11: ='Obligation 3 Amort. Zero coupon'!G23 -> 4.6151006
A12: Risque de taux | B12: ⬇ Faible | C12: ⬆ Moyen | D12: ⬆⬆ Élevé
